.gitignore
.pre-commit-config.yaml
CHANGES.txt
LICENSE
MANIFEST.in
Makefile
README
README.rst
TODO
pyproject.toml
requirements.txt
setup.cfg
setup.py
./mapgenerator/__init__.py
./mapgenerator/mg_exceptions.py
./mapgenerator/plotting/__init__.py
./mapgenerator/plotting/config.py
./mapgenerator/plotting/definitions.py
./mapgenerator/plotting/plotmap.py
./mapgenerator/plotting/timeseries.py
./mapgenerator/plotting/tools.py
bin/map_main.py
bin/mg
mapgenerator/__init__.py
mapgenerator/mg_exceptions.py
mapgenerator.egg-info/PKG-INFO
mapgenerator.egg-info/SOURCES.txt
mapgenerator.egg-info/dependency_links.txt
mapgenerator.egg-info/requires.txt
mapgenerator.egg-info/top_level.txt
mapgenerator/evaluation/DAevaluator.py
mapgenerator/plotting/__init__.py
mapgenerator/plotting/config.py
mapgenerator/plotting/definitions.py
mapgenerator/plotting/plotmap.py
mapgenerator/plotting/timeseries.py
mapgenerator/plotting/tools.py
mapgenerator/sample/__init__.py
mapgenerator/sample/core.py
mapgenerator/sample/helpers.py
mapgenerator/test/__init__.py
mapgenerator/test/unit/__init__.py
mapgenerator/test/unit/test_argument_parser.py
mapgenerator/test/unit/test_environment.py
mapgenerator/test/unit/test_http.py
mapgenerator/utils/cross.py
mapgenerator/utils/iplot.py
mapgenerator/utils/map_generator.py
mapgenerator/utils/old_map_utils.py
mapgenerator/utils/old_sds_map_generator.py
mapgenerator/utils/run_mn.sh
mapgenerator/utils/tseries.py