Metadata-Version: 2.1
Name: mapgenerator
Version: 1.0.6
Summary: Map Generator is a tool that provides easy to use 2D plotting functions for Earth sciences datasets.
Home-page: https://pypi.org/project/MapGenerator
Author: Francesco Benincasa
Author-email: francesco.benincasa@bsc.es
License: Apache 2.0
Keywords: earth sciences,weather,climate,air quality,2D maps
Platform: UNKNOWN
Classifier: Programming Language :: Python :: 3
Classifier: License :: OSI Approved :: Apache Software License
Classifier: Operating System :: POSIX :: Linux
Requires-Python: >=3.6
